shaker/__init__.py
shaker/lib.py
shaker/version.py
shaker/agent/__init__.py
shaker/agent/agent.py
shaker/engine/__init__.py
shaker/engine/all_in_one.py
shaker/engine/config.py
shaker/engine/deploy.py
shaker/engine/image_builder.py
shaker/engine/messaging.py
shaker/engine/quorum.py
shaker/engine/report.py
shaker/engine/server.py
shaker/engine/sla.py
shaker/engine/spot.py
shaker/engine/utils.py
shaker/engine/writer.py
shaker/engine/aggregators/__init__.py
shaker/engine/aggregators/base.py
shaker/engine/aggregators/traffic.py
shaker/engine/executors/__init__.py
shaker/engine/executors/base.py
shaker/engine/executors/flent.py
shaker/engine/executors/iperf.py
shaker/engine/executors/netperf.py
shaker/engine/executors/shell.py
shaker/openstack/__init__.py
shaker/openstack/clients/__init__.py
shaker/openstack/clients/glance.py
shaker/openstack/clients/heat.py
shaker/openstack/clients/neutron.py
shaker/openstack/clients/nova.py
shaker/openstack/clients/openstack.py
shaker/resources/image_builder_templates/centos.yaml
shaker/resources/image_builder_templates/debian.yaml
shaker/resources/image_builder_templates/ubuntu.yaml
shaker/resources/image_elements/shaker/README.rst
shaker/resources/image_elements/shaker/element-deps
shaker/resources/image_elements/shaker-agent/README.rst
shaker/resources/image_elements/shaker-agent/element-deps
shaker/resources/image_elements/shaker-agent/package-installs.yaml
shaker/resources/image_elements/shaker-agent/pkg-map
shaker/resources/image_elements/shaker-agent/install.d/15-shaker-essentials
shaker/resources/image_elements/shaker-agent/install.d/51-shaker-agent
shaker/resources/image_elements/shaker-sys-opts/post-install.d/50-mtu
shaker/resources/image_elements/shaker-tools/README.rst
shaker/resources/image_elements/shaker-tools/element-deps
shaker/resources/image_elements/shaker-tools/install.d/40-iperf
shaker/resources/image_elements/shaker-tools/install.d/42-netperf
shaker/resources/image_elements/shaker-tools/install.d/44-flent
pyshaker-1.4.2.dist-info/AUTHORS
pyshaker-1.4.2.dist-info/LICENSE
pyshaker-1.4.2.dist-info/METADATA
pyshaker-1.4.2.dist-info/WHEEL
pyshaker-1.4.2.dist-info/entry_points.txt
pyshaker-1.4.2.dist-info/pbr.json
pyshaker-1.4.2.dist-info/top_level.txt
pyshaker-1.4.2.dist-info/RECORD
